plumed_nodes/__init__.py
plumed_nodes/actions.py
plumed_nodes/calc.py
plumed_nodes/cvs.py
plumed_nodes/interfaces.py
plumed_nodes/metadynamics.py
plumed_nodes/nodes.py
plumed_nodes/selectors.py
plumed_nodes-0.1.0a6.dist-info/METADATA
plumed_nodes-0.1.0a6.dist-info/WHEEL
plumed_nodes-0.1.0a6.dist-info/entry_points.txt
plumed_nodes-0.1.0a6.dist-info/RECORD
