Metadata-Version: 2.4
Name: plumed-nodes
Version: 0.1.0a6
Summary: Python interfaces for the plumed library.
Requires-Python: >=3.11
Requires-Dist: ase>=3.25.0
Requires-Dist: plumed>=2.9.0
Requires-Dist: rdkit2ase>=0.1.13
Requires-Dist: zntrack>=0.8.9
